
{
"fresh_text": "\u70ed\u699c\u5df2\u66f4\u65b0",
"paging": {
"is_end": true,
"previous": "",
"next": ""
},
"data": [{
"style_type": "1",
"detail_text": "893 \u4e07\u9886\u57df\u70ed\u5ea6",
"target": {
"bound_topic_ids": [1718, 2102, 5419, 158305, 552667],
"excerpt": "",
"answer_count": 82,
"is_following": false,
"id": 367586824,
"author": {
"headline": "",
"avatar_url": "https://pic4.zhimg.com/aadd7b895_s.jpg",
"name": "\u7528\u6237",
"url": "",
"url_token": "",
"type": "people",
"user_type": "people",
"id": "0"
},
"url": "https://api.zhihu.com/questions/367586824",
"title": "\u7535\u89c6\u5267\u300a\u60f3\u89c1\u4f60\u300b\u6709\u4ec0\u4e48\u7ec6\u601d\u6781\u6050\u7684\u7ec6\u8282\uff1f",
"created": 1579762468,
"comment_count": 2,
"follower_count": 959,
"type": "question"
},
"trend": 0,
"debut": false,
"card_id": "Q_367586824",
"children": [{
"type": "answer",
"thumbnail": "https://pic2.zhimg.com/50/v2-ede82357a5382e9dafb13287541734f6_b.jpg"
}],
"attached_info": "CkQIzL+YpujNnf07EAMaCDQzOTY0MTAyIKSGpfEFMAI4vwdAAHIJMzY3NTg2ODI0eACqAQ5iaWxsYm9hcmQtZmlsbdIBAA==",
"type": "hot_list_feed",
"id": "0_1580581229.68"
}, {
"style_type": "1",
"detail_text": "494 \u4e07\u9886\u57df\u70ed\u5ea6",
"target": {
"bound_topic_ids": [156252],
"excerpt": "",
"answer_count": 752,
"is_following": false,
"id": 41072763,
"author": {
"headline": "",
"avatar_url": "https://pic4.zhimg.com/aadd7b895_s.jpg",
"name": "\u7528\u6237",
"url": "",
"url_token": "",
"type": "people",
"user_type": "people",
"id": "0"
},
"url": "https://api.zhihu.com/questions/41072763",
"title": "\u621112\u5c81\u7684\u513f\u5b50\u6628\u5929\u4e70\u4e86\u7b2c\u4e8c\u672c\u300a\u5341\u5b97\u7f6a\u300b\uff0c\u8981\u4e0d\u8981\u5236\u6b62\u4ed6\u770b\u5462\uff1f",
"created": 1457238803,
"comment_count": 37,
"follower_count": 1094,
"type": "question"
},
"trend": 0,
"debut": false,
"card_id": "Q_41072763",
"children": [{
"type": "answer",
"thumbnail": "https://pic2.zhimg.com/80/v2-bbafe17d69ee0e03fb6763d328ed3bfb_hd.jpg"
}],
"attached_info": "CkIIzL+YpujNnf07EAMaBzg2MzY0MjQgk+butgUwJTjGCEABcgg0MTA3Mjc2M3gAqgEOYmlsbGJvYXJkLWZpbG3SAQA=",
"type": "hot_list_feed",
"id": "1_1580581229.68"
}, {
"style_type": "1",
"detail_text": "394 \u4e07\u9886\u57df\u70ed\u5ea6",
"target": {
"bound_topic_ids": [5419, 12945, 29916],
"excerpt": "",
"answer_count": 1306,
"is_following": false,
"id": 366696183,
"author": {
"headline": "",
"avatar_url": "https://pic4.zhimg.com/aadd7b895_s.jpg",
"name": "\u7528\u6237",
"url": "",
"url_token": "",
"type": "people",
"user_type": "people",
"id": "0"
},
"url": "https://api.zhihu.com/questions/366696183",
"title": "\u4f60\u89c9\u5f97\u53e4\u88c5\u7537\u6f14\u5458\u8c01\u6700\u597d\u770b\uff1f",
"created": 1579237668,
"comment_count": 45,
"follower_count": 1648,
"type": "question"
},
"trend": 0,
"debut": false,
"card_id": "Q_366696183",
"children": [{
"type": "answer",
"thumbnail": "https://pic1.zhimg.com/50/v2-79bbab79671ed3839daf6233c8a3220d_b.jpg"
}],
"attached_info": "CkQIzL+YpujNnf07EAMaCDQzNzY2NDA2IKSChfEFMC048AxAAnIJMzY2Njk2MTgzeACqAQ5iaWxsYm9hcmQtZmlsbdIBAA==",
"type": "hot_list_feed",
"id": "2_1580581229.68"
}, {
"style_type": "1",
"detail_text": "280 \u4e07\u9886\u57df\u70ed\u5ea6",
"target": {
"bound_topic_ids": [4117],
"excerpt": "",
"answer_count": 69,
"is_following": false,
"id": 321985437,
"author": {
"headline": "",
"avatar_url": "https://pic4.zhimg.com/aadd7b895_s.jpg",
"name": "\u7528\u6237",
"url": "",
"url_token": "",
"type": "people",
"user_type": "people",
"id": "0"
},
"url": "https://api.zhihu.com/questions/321985437",
"title": "\u5982\u4f55\u8bc4\u4ef7\u65e5\u5267\u300a\u53ef\u4ee5\u4e0d\u53ef\u4ee5\u300b\uff1f",
"created": 1556373514,
"comment_count": 0,
"follower_count": 519,
"type": "question"
},
"trend": 0,
"debut": false,
"card_id": "Q_321985437",
"children": [{
"type": "answer",
"thumbnail": "https://pic3.zhimg.com/50/v2-c6727b06a109571b85fe9ca63e6253dd_b.jpg"
}],
"attached_info": "CkQIzL+YpujNnf07EAMaCDMzODI4NDU2IIrAkeYFMAA4hwRAA3IJMzIxOTg1NDM3eACqAQ5iaWxsYm9hcmQtZmlsbdIBAA==",
"type": "hot_list_feed",
"id": "3_1580581229.68"
}, {
"style_type": "1",
"detail_text": "271 \u4e07\u9886\u57df\u70ed\u5ea6",
"target": {
"bound_topic_ids": [2102, 7751, 29916, 44844],
"excerpt": "\u5b8b\u831c\uff0c\u5b8b\u5a01\u9f99\u4e3b\u6f14\u7684\u300a\u4e0b\u4e00\u7ad9\u5e78\u798f\u300b 1.26\u5728\u6e56\u5357\u536b\u89c6\u64ad\u51fa",
"answer_count": 142,
"is_following": false,
"id": 368045938,
"author": {
"headline": "",
"avatar_url": "https://pic4.zhimg.com/aadd7b895_s.jpg",
"name": "\u7528\u6237",
"url": "",
"url_token": "",
"type": "people",
"user_type": "people",
"id": "0"
},
"url": "https://api.zhihu.com/questions/368045938",
"title": "\u5982\u4f55\u8bc4\u4ef7\u7535\u89c6\u5267\u300a\u4e0b\u4e00\u7ad9\u662f\u5e78\u798f\u300b?",
"created": 1580056048,
"comment_count": 0,
"follower_count": 239,
"type": "question"
},
"trend": 0,
"debut": false,
"card_id": "Q_368045938",
"children": [{
"type": "answer",
"thumbnail": "https://pic2.zhimg.com/80/v2-0f3e9bcbff35225226086ca4e107ad0e_hd.jpg"
}],
"attached_info": "CkQIzL+YpujNnf07EAMaCDQ0MDY1ODcwIPD7tvEFMAA47wFABHIJMzY4MDQ1OTM4eACqAQ5iaWxsYm9hcmQtZmlsbdIBAA==",
"type": "hot_list_feed",
"id": "4_1580581229.68"
}, {
"style_type": "1",
"detail_text": "213 \u4e07\u9886\u57df\u70ed\u5ea6",
"target": {
"bound_topic_ids": [17945, 18809, 400649],
"excerpt": "[\u89c6\u9891]",
"answer_count": 58,
"is_following": false,
"id": 368963611,
"author": {
"headline": "",
"avatar_url": "https://pic4.zhimg.com/aadd7b895_s.jpg",
"name": "\u7528\u6237",
"url": "",
"url_token": "",
"type": "people",
"user_type": "people",
"id": "0"
},
"url": "https://api.zhihu.com/questions/368963611",
"title": "\u5982\u4f55\u8bc4\u4ef7\u300a\u901f\u5ea6\u4e0e\u6fc0\u60c5 9\u300b \u9996\u652f\u9884\u544a\u7247\uff1f",
"created": 1580529660,
"comment_count": 4,
"follower_count": 112,
"type": "question"
},
"trend": 0,
"debut": false,
"card_id": "Q_368963611",
"children": [{
"type": "answer",
"thumbnail": "https://pic1.zhimg.com/50/v2-89643bc14db8f17c9942975f8e1c93f0_b.jpg"
}],
"attached_info": "CkMIzL+YpujNnf07EAMaCDQ0MjY5NjU1IPzv0/EFMAQ4cEAFcgkzNjg5NjM2MTF4AKoBDmJpbGxib2FyZC1maWxt0gEA",
"type": "hot_list_feed",
"id": "5_1580581229.69"
}, {
"style_type": "1",
"detail_text": "151 \u4e07\u9886\u57df\u70ed\u5ea6",
"target": {
"bound_topic_ids": [4105, 7751, 221494],
"excerpt": "\u6211\u4e2a\u4eba\u611f\u89c9\u662f\u4e0d\u662f\u7537\u4e3b\u8eab\u8fb9\u5973\u751f\u592a\u5c11\u4e86?\u6c42\u89e3",
"answer_count": 64,
"is_following": false,
"id": 367541000,
"author": {
"headline": "",
"avatar_url": "https://pic4.zhimg.com/aadd7b895_s.jpg",
"name": "\u7528\u6237",
"url": "",
"url_token": "",
"type": "people",
"user_type": "people",
"id": "0"
},
"url": "https://api.zhihu.com/questions/367541000",
"title": "\u300a\u9526\u8863\u4e4b\u4e0b\u300b\u4e2d\u7537\u4e3b\u5230\u5e95\u559c\u6b22\u5973\u4e3b\u54ea\u4e00\u70b9\uff1f",
"created": 1579739163,
"comment_count": 1,
"follower_count": 171,
"type": "question"
},
"trend": 0,
"debut": false,
"card_id": "Q_367541000",
"children": [{
"type": "answer",
"thumbnail": "https://pic3.zhimg.com/50/v2-a22b122799dd0f536d96995f572fd872_b.jpg"
}],
"attached_info": "CkQIzL+YpujNnf07EAMaCDQzOTUzOTkzIJvQo/EFMAE4qwFABnIJMzY3NTQxMDAweACqAQ5iaWxsYm9hcmQtZmlsbdIBAA==",
"type": "hot_list_feed",
"id": "6_1580581229.69"
}, {
"style_type": "1",
"detail_text": "150 \u4e07\u9886\u57df\u70ed\u5ea6",
"target": {
"bound_topic_ids": [68, 2191, 115430],
"excerpt": "",
"answer_count": 982,
"is_following": false,
"id": 366245943,
"author": {
"headline": "",
"avatar_url": "https://pic4.zhimg.com/aadd7b895_s.jpg",
"name": "\u7528\u6237",
"url": "",
"url_token": "",
"type": "people",
"user_type": "people",
"id": "0"
},
"url": "https://api.zhihu.com/questions/366245943",
"title": "\u8fc4\u4eca\u4e3a\u6b62\u54ea\u90e8\u7535\u5f71\u6700\u611f\u52a8\u4f60\uff1f",
"created": 1578984544,
"comment_count": 5,
"follower_count": 1822,
"type": "question"
},
"trend": 0,
"debut": false,
"card_id": "Q_366245943",
"children": [{
"type": "answer",
"thumbnail": "https://pic2.zhimg.com/50/v2-965cc02f042889819b858ad214df0465_b.jpg"
}],
"attached_info": "CkQIzL+YpujNnf07EAMaCDQzNjY2MzQxIODI9fAFMAU4ng5AB3IJMzY2MjQ1OTQzeACqAQ5iaWxsYm9hcmQtZmlsbdIBAA==",
"type": "hot_list_feed",
"id": "7_1580581229.69"
}, {
"style_type": "1",
"detail_text": "147 \u4e07\u9886\u57df\u70ed\u5ea6",
"target": {
"bound_topic_ids": [552667],
"excerpt": "\u8fd8\u6ca1\u6709\u5f00\u59cb\u770b\u8fd9\u90e8\u5267\uff0c\u5c31\u5148\u88ab\u7f51\u4e0a\u7684\u89e3\u6790\u5438\u5f15\u4e86\u3002\u96f6\u96f6\u6563\u6563\u770b\u4e86\u5f88\u591a\u89e3\u6790\uff0c\u5927\u6982\u4e86\u89e3\u8fd9\u4e2a\u5faa\u73af\u3002 \u6211\u5148\u4e0d\u7ba1\u8fd9\u4e2a\u5faa\u73af\u3002\u6545\u4e8b\u5f00\u5934\u76842019\u5e74\uff0c\u738b\u8be0\u80dc\u6b7b\u4e86\uff0c\u674e\u5b50\u7ef4\u8fd8\u5728\uff0c\u9ec4\u96e8\u8431\u4e5f\u8fd8\u5728\u3002\u4e3a\u4ec0\u4e48\u674e\u5b50\u7ef4\u4e0d\u76f4\u63a5\u4ee5\u65b0\u7684\u8eab\u4efd\u53bb\u8ddf\u9ec4\u96e8\u8431\u5728\u4e00\u8d77\uff1f\u53cd\u800c\u8981\u5979\u7ee7\u7eed\u8fdb\u5165\u5faa\u73af\uff1f \u4e0d\u8fdb\u5165\u5faa\u73af\u7684\u8bdd\uff0c1999\u5e74\u7684\u51f6\u6740\u6848\u4f1a\u7ee7\u7eed\u53d1\u751f\u5417\uff0c2019\u5e74\u7684\u9ec4\u96e8\u8431\u4f1a\u7a81\u7136\u6b7b\u53bb\u5417\uff1f",
"answer_count": 21,
"is_following": false,
"id": 366629691,
"author": {
"headline": "",
"avatar_url": "https://pic4.zhimg.com/aadd7b895_s.jpg",
"name": "\u7528\u6237",
"url": "",
"url_token": "",
"type": "people",
"user_type": "people",
"id": "0"
},
"url": "https://api.zhihu.com/questions/366629691",
"title": "\u300a\u60f3\u89c1\u4f60\u300b\u91cc\uff0c\u4e3a\u4ec0\u4e48\u8001\u674e\u5b50\u7ef4\u4e0d\u76f4\u63a5\u8ddf\u9ec4\u96e8\u8431\u5728\u4e00\u8d77\uff1f",
"created": 1579185656,
"comment_count": 0,
"follower_count": 75,
"type": "question"
},
"trend": 0,
"debut": false,
"card_id": "Q_366629691",
"children": [{
"type": "answer",
"thumbnail": "https://pic2.zhimg.com/50/v2-84283e01524efbc6848fab6c26871fb2_b.jpg"
}],
"attached_info": "CkMIzL+YpujNnf07EAMaCDQzNzUxNjMzIPjrgfEFMAA4S0AIcgkzNjY2Mjk2OTF4AKoBDmJpbGxib2FyZC1maWxt0gEA",
"type": "hot_list_feed",
"id": "8_1580581229.69"
}, {
"style_type": "1",
"detail_text": "93 \u4e07\u9886\u57df\u70ed\u5ea6",
"target": {
"bound_topic_ids": [74, 1309, 4117, 7751, 33917],
"excerpt": "",
"answer_count": 1712,
"is_following": false,
"id": 58473020,
"author": {
"headline": "",
"avatar_url": "https://pic4.zhimg.com/aadd7b895_s.jpg",
"name": "\u7528\u6237",
"url": "",
"url_token": "",
"type": "people",
"user_type": "people",
"id": "0"
},
"url": "https://api.zhihu.com/questions/58473020",
"title": "\u4f60\u770b\u8fc7\u6700\u597d\u7684\u4e94\u90e8\u65e5\u5267\u662f\u4ec0\u4e48\uff1f",
"created": 1492136221,
"comment_count": 30,
"follower_count": 30101,
"type": "question"
},
"trend": 0,
"debut": false,
"card_id": "Q_58473020",
"children": [{
"type": "answer",
"thumbnail": "https://pic2.zhimg.com/50/v2-399d00583048fa6cfe51edccb215eb79_b.jpg"
}],
"attached_info": "CkQIzL+YpujNnf07EAMaCDE1NjEwODkxIJ3iwMcFMB44lesBQAlyCDU4NDczMDIweACqAQ5iaWxsYm9hcmQtZmlsbdIBAA==",
"type": "hot_list_feed",
"id": "9_1580581229.69"
}, {
"style_type": "1",
"detail_text": "79 \u4e07\u9886\u57df\u70ed\u5ea6",
"target": {
"bound_topic_ids": [119, 161, 988, 26323, 31898],
"excerpt": "",
"answer_count": 1573,
"is_following": false,
"id": 315958918,
"author": {
"headline": "",
"avatar_url": "https://pic4.zhimg.com/aadd7b895_s.jpg",
"name": "\u7528\u6237",
"url": "",
"url_token": "",
"type": "people",
"user_type": "people",
"id": "0"
},
"url": "https://api.zhihu.com/questions/315958918",
"title": "Bilibili\uff08\u54d4\u54e9\u54d4\u54e9\uff09\u4e0a\u6709\u54ea\u4e9b\u503c\u5f97\u4e00\u770b\u7684\u7eaa\u5f55\u7247\uff1f",
"created": 1552574617,
"comment_count": 39,
"follower_count": 130999,
"type": "question"
},
"trend": 0,
"debut": false,
"card_id": "Q_315958918",
"children": [{
"type": "answer",
"thumbnail": "https://pic2.zhimg.com/80/v2-1e3350ea00a579c863c016f875e66d46_hd.jpg"
}],
"attached_info": "CkUIzL+YpujNnf07EAMaCDMyNDg5NTgzIJnRqeQFMCc4t/8HQApyCTMxNTk1ODkxOHgAqgEOYmlsbGJvYXJkLWZpbG3SAQA=",
"type": "hot_list_feed",
"id": "10_1580581229.69"
}, {
"style_type": "1",
"detail_text": "77 \u4e07\u9886\u57df\u70ed\u5ea6",
"target": {
"bound_topic_ids": [542, 2058, 7246, 14270, 100255],
"excerpt": "",
"answer_count": 2848,
"is_following": false,
"id": 47536117,
"author": {
"headline": "",
"avatar_url": "https://pic4.zhimg.com/aadd7b895_s.jpg",
"name": "\u7528\u6237",
"url": "",
"url_token": "",
"type": "people",
"user_type": "people",
"id": "0"
},
"url": "https://api.zhihu.com/questions/47536117",
"title": "\u4e3a\u4ec0\u4e48\u540c\u6837\u662f\u63cf\u5199\u5962\u4f88\u534e\u7f8e\u7684\u751f\u6d3b\uff0c\u300a\u5c0f\u65f6\u4ee3\u300b\u7ed9\u4eba\u5f88\u88c5\u903c\u7684\u611f\u89c9\uff0c\u800c\u300a\u7ea2\u697c\u68a6\u300b\u6ca1\u6709\uff1f",
"created": 1466147787,
"comment_count": 148,
"follower_count": 14797,
"type": "question"
},
"trend": 0,
"debut": false,
"card_id": "Q_47536117",
"children": [{
"type": "answer",
"thumbnail": "https://pic3.zhimg.com/50/v2-f02c72db78f0e9784ce26151aa817bb5_b.jpg"
}],
"attached_info": "CkQIzL+YpujNnf07EAMaCDExMjI5Mzg0IMvHjrsFMJQBOM1zQAtyCDQ3NTM2MTE3eACqAQ5iaWxsYm9hcmQtZmlsbdIBAA==",
"type": "hot_list_feed",
"id": "11_1580581229.69"
}, {
"style_type": "1",
"detail_text": "77 \u4e07\u9886\u57df\u70ed\u5ea6",
"target": {
"bound_topic_ids": [851, 23232, 36541],
"excerpt": "\u7247\u540d\u300aRise of empires: Ottoman\u300b \u7cbe\u7f57\u72c2\u6012\uff1f",
"answer_count": 21,
"is_following": false,
"id": 367911891,
"author": {
"headline": "",
"avatar_url": "https://pic4.zhimg.com/aadd7b895_s.jpg",
"name": "\u7528\u6237",
"url": "",
"url_token": "",
"type": "people",
"user_type": "people",
"id": "0"
},
"url": "https://api.zhihu.com/questions/367911891",
"title": "\u5982\u4f55\u8bc4\u4ef7Netflix\u65b0\u7247\u300a\u5e1d\u56fd\u5d1b\u8d77\uff1a\u5965\u65af\u66fc\u300b?",
"created": 1579973917,
"comment_count": 3,
"follower_count": 56,
"type": "question"
},
"trend": 0,
"debut": false,
"card_id": "Q_367911891",
"children": [{
"type": "answer",
"thumbnail": "https://pic2.zhimg.com/50/v2-5637e9db7ad5444599dc60bfc4073196_b.jpg"
}],
"attached_info": "CkMIzL+YpujNnf07EAMaCDQ0MDM2MTU2IJ36sfEFMAM4OEAMcgkzNjc5MTE4OTF4AKoBDmJpbGxib2FyZC1maWxt0gEA",
"type": "hot_list_feed",
"id": "12_1580581229.69"
}, {
"style_type": "1",
"detail_text": "76 \u4e07\u9886\u57df\u70ed\u5ea6",
"target": {
"bound_topic_ids": [23133, 65262, 205633],
"excerpt": "",
"answer_count": 23,
"is_following": false,
"id": 365694230,
"author": {
"headline": "",
"avatar_url": "https://pic4.zhimg.com/aadd7b895_s.jpg",
"name": "\u7528\u6237",
"url": "",
"url_token": "",
"type": "people",
"user_type": "people",
"id": "0"
},
"url": "https://api.zhihu.com/questions/365694230",
"title": "\u300a\u6b66\u6797\u5916\u4f20\u300b\u91cc\u4f5f\u638c\u67dc\u6bcf\u6708\u53ea\u7ed9\u4f19\u8ba1\u4e8c\u94b1\u94f6\u5b50\uff0c\u771f\u7684\u5c11\u5417\uff1f",
"created": 1578664392,
"comment_count": 2,
"follower_count": 33,
"type": "question"
},
"trend": 0,
"debut": false,
"card_id": "Q_365694230",
"children": [{
"type": "answer",
"thumbnail": "https://pic3.zhimg.com/50/v2-0c956668595582eeda51247a7fd5dde8_b.jpg"
}],
"attached_info": "CkMIzL+YpujNnf07EAMaCDQzNTQzMzQ5IMiD4vAFMAI4IUANcgkzNjU2OTQyMzB4AKoBDmJpbGxib2FyZC1maWxt0gEA",
"type": "hot_list_feed",
"id": "13_1580581229.69"
}, {
"style_type": "1",
"detail_text": "65 \u4e07\u9886\u57df\u70ed\u5ea6",
"target": {
"bound_topic_ids": [68, 73, 6311, 50778, 67520],
"excerpt": "\u7a81\u7136\u89e6\u5230\u7684\u6cea\u70b9\uff0c\u611f\u52a8\u7684\u90fd\u662f\u4ec0\u4e48\u5730\u65b9",
"answer_count": 22,
"is_following": false,
"id": 341437003,
"author": {
"headline": "",
"avatar_url": "https://pic4.zhimg.com/aadd7b895_s.jpg",
"name": "\u7528\u6237",
"url": "",
"url_token": "",
"type": "people",
"user_type": "people",
"id": "0"
},
"url": "https://api.zhihu.com/questions/341437003",
"title": "\u6709\u4ec0\u4e48\u8ba9\u4eba\u77ac\u95f4\u6cea\u76ee\u7684\u5c0f\u8bf4\u3001\u89c6\u9891\u6216\u7535\u5f71\u7247\u6bb5\uff1f",
"created": 1566211119,
"comment_count": 0,
"follower_count": 51,
"type": "question"
},
"trend": 0,
"debut": false,
"card_id": "Q_341437003",
"children": [{
"type": "answer",
"thumbnail": "https://pic4.zhimg.com/50/v2-b2a977ef142b7552378e3059856f9b47_b.jpg"
}],
"attached_info": "CkMIzL+YpujNnf07EAMaCDM4MTUxNzg1IK/46eoFMAA4M0AOcgkzNDE0MzcwMDN4AKoBDmJpbGxib2FyZC1maWxt0gEA",
"type": "hot_list_feed",
"id": "14_1580581229.69"
}]
}

